<LevelActor type="Asset_TwistedPT" displayName="PineTreeTwisted" tileID="3" exportType="1">
    <LevelCollider type="2">
        <Offset x="0" y="3" z="0"/>
        <Color x="0" y="1" z="0"/>
        <IDs ID="1428" parentID="0"/>
        <Behavior Type="0"/>
        <GenParent value="true"/>
        <Rotation x="0" y="0" z="0"/>
        <HalfLengths x="1.5" y="5" z="1.5"/>
    </LevelCollider>
    <LevelModel>
        <ModelName>Twisted_pineTree1</ModelName>
    </LevelModel>
    <LevelTransform>
        <Position x="464.75" y="47.729248" z="210.125"/>
        <Rotation x="0" y="0" z="0"/>
        <Scale x="1" y="1" z="1"/>
        <Export e="true"/>
    </LevelTransform>
</LevelActor>
